{
"type": "FeatureCollection",
"name": "bounding_box_wgs84",
"crs": { "type": "name", "properties": { "name": "urn:ogc:def:crs:OGC:1.3:CRS84" } },
"features": [
{
	"type":"Feature",
	"geometry": {
		"type": "Point",
		"coordinates": [ -89.3792724609375,
              14.753635331540442 ]
	}
},
{
	"type":"Feature",
	"geometry": {
		"type": "Point",
		"coordinates": [ -89.351806640625,
              14.508463695004872 ]
	}
},
{
	"type":"Feature",
	"geometry": {
		"type": "Point",
		"coordinates": [ -90.051806640625,
              14.508463695004872 ]
	}
}
]
}