{
"type": "FeatureCollection",
"name": "zoomBoxWgs84",
"crs": { "type": "name", "properties": { "name": "urn:ogc:def:crs:OGC:1.3:CRS84" } },
"features": [
{ "type": "Feature", "properties": { "id": 1, "vertex_index": 0, "vertex_part": 0, "vertex_part_ring": 0, "vertex_part_index": 0, "distance": 0.0, "angle": 314.99999999999915 }, "geometry": { "type": "Point", "coordinates": [ -92.386896992036583, 14.738190167336922 ] } },
{ "type": "Feature", "properties": { "id": 1, "vertex_index": 1, "vertex_part": 0, "vertex_part_ring": 0, "vertex_part_index": 1, "distance": 170393.86400188727, "angle": 45.000000000000007 }, "geometry": { "type": "Point", "coordinates": [ -92.403236438794409, 16.27782485498982 ] } },
{ "type": "Feature", "properties": { "id": 1, "vertex_index": 2, "vertex_part": 0, "vertex_part_ring": 0, "vertex_part_index": 2, "distance": 356737.83856102912, "angle": 135.0 }, "geometry": { "type": "Point", "coordinates": [ -90.659613540238112, 16.288236427981811 ] } },
{ "type": "Feature", "properties": { "id": 1, "vertex_index": 3, "vertex_part": 0, "vertex_part_ring": 0, "vertex_part_index": 3, "distance": 527131.70256291074, "angle": 224.99999999999912 }, "geometry": { "type": "Point", "coordinates": [ -90.656383278880384, 14.748526281341883 ] } },
{ "type": "Feature", "properties": { "id": 1, "vertex_index": 4, "vertex_part": 0, "vertex_part_ring": 0, "vertex_part_index": 4, "distance": 713475.67712205253, "angle": 314.99999999999915 }, "geometry": { "type": "Point", "coordinates": [ -92.386896992036583, 14.738190167336922 ] } }
]
}
